{"_cloudLastModified":1438692804596914,"_cloudCreated":1438692804596830,"_store":{"store":{"http://www.math.uga.edu/%7Epete/teaching.html":{"_bookmarkDateAdded":1254929184000000,"_bookmarkTags":[],"_bookmarkLastModified":1438675428320000,"_bookmarkUrl":"http://www.math.uga.edu/%7Epete/teaching.html","_bookmarkTitle":"http://www.math.uga.edu/~pete/teaching.html"},"http://sacred-economics.com/":{"_bookmarkDateAdded":1367255442000000,"_bookmarkTags":[],"_bookmarkLastModified":1438675421548000,"_bookmarkUrl":"http://sacred-economics.com/","_bookmarkTitle":"Sacred Economics | Charles Eisenstein | Money, Gift and Society in the Age of Transition."}}}}