{"_cloudLastModified":1445264616773568,"_cloudCreated":1438692804613998,"_store":{"store":{"http://courses.csail.mit.edu/":{"_bookmarkDateAdded":1238175424000000,"_bookmarkTags":[],"_bookmarkLastModified":1438675429165000,"_bookmarkUrl":"http://courses.csail.mit.edu/","_bookmarkTitle":"courses.csail.mit.edu"},"http://math.mit.edu/%7Erstan/s34/":{"_bookmarkDateAdded":1258828231000000,"_bookmarkTags":[],"_bookmarkLastModified":1438675428056000,"_bookmarkUrl":"http://math.mit.edu/%7Erstan/s34/","_bookmarkTitle":"18.S34 Home Page"},"https://work.caltech.edu/telecourse.html":{"_bookmarkDateAdded":1416403970000000,"_bookmarkTags":[],"_bookmarkLastModified":1438695158553000,"_bookmarkUrl":"https://work.caltech.edu/telecourse.html","_bookmarkTitle":"Learning From Data - Online Course (MOOC)"},"https://github.com/kwf/GQFC":{"_bookmarkDateAdded":1441557556628000,"_bookmarkTags":["haskell"],"_bookmarkLastModified":1441557556646000,"_bookmarkUrl":"https://github.com/kwf/GQFC","_bookmarkTitle":"kwf/GQFC"},"http://www.cs.brown.edu/courses/csci1550/":{"_bookmarkDateAdded":1262681971000000,"_bookmarkTags":[],"_bookmarkLastModified":1438675427808000,"_bookmarkUrl":"http://www.cs.brown.edu/courses/csci1550/","_bookmarkTitle":"CS 155 - Probabilistic Methods in Computer Science"}}}}