{"_cloudLastModified":1438692804602169,"_cloudCreated":1438692794666725,"_store":{"store":{"http://www.levibotelho.com/development/commit-a-file-with-the-github-api/":{"_bookmarkDateAdded":1418365954840000,"_bookmarkTags":[],"_bookmarkLastModified":1418365955181000,"_bookmarkUrl":"http://www.levibotelho.com/development/commit-a-file-with-the-github-api/","_bookmarkTitle":"Commit a file with the GitHub API – Levi Botelho's Coding Blog"},"http://www.ams.sunysb.edu/%7Ejsbm/":{"_bookmarkDateAdded":1275930967000000,"_bookmarkTags":[],"_bookmarkLastModified":1438675425557000,"_bookmarkUrl":"http://www.ams.sunysb.edu/%7Ejsbm/","_bookmarkTitle":"Personal Page of Joe Mitchell"}}}}