{"_cloudLastModified":1438692804589490,"_cloudCreated":1438692804589373,"_store":{"store":{"http://www.acm.org/membership/acm-bulletin-archive/march-19-2013-people-of-acm-christos-papadimitriou":{"_bookmarkDateAdded":1369244773000000,"_bookmarkTags":[],"_bookmarkLastModified":1438675421071000,"_bookmarkUrl":"http://www.acm.org/membership/acm-bulletin-archive/march-19-2013-people-of-acm-christos-papadimitriou","_bookmarkTitle":"March 19, 2013: People of ACM: Christos Papadimitriou — Association for Computing Machinery"},"http://stellar.mit.edu/S/course/6/fa09/6.046/":{"_bookmarkDateAdded":1261138621000000,"_bookmarkTags":[],"_bookmarkLastModified":1438675427973000,"_bookmarkUrl":"http://stellar.mit.edu/S/course/6/fa09/6.046/","_bookmarkTitle":"6.046J/18.410J Class Home"}}}}