{"_cloudLastModified":1445943998534122,"_cloudCreated":1438692794645430,"_store":{"store":{"http://theory.stanford.edu/~tim/":{"_bookmarkDateAdded":1434127782798000,"_bookmarkTags":["tcs"],"_bookmarkLastModified":1434127782822000,"_bookmarkUrl":"http://theory.stanford.edu/~tim/","_bookmarkTitle":"Tim Roughgarden's Homepage"},"http://spinejs.com/":{"_bookmarkDateAdded":1330955165000000,"_bookmarkTags":[],"_bookmarkLastModified":1438675422947000,"_bookmarkUrl":"http://spinejs.com/","_bookmarkTitle":"Spine"},"http://cseweb.ucsd.edu/classes/fa09/cse21/":{"_bookmarkDateAdded":1264518546000000,"_bookmarkTags":[],"_bookmarkLastModified":1438675427630000,"_bookmarkUrl":"http://cseweb.ucsd.edu/classes/fa09/cse21/","_bookmarkTitle":"CSE 21"},"http://bigocheatsheet.com/#data-structures":{"_bookmarkDateAdded":1440043063917000,"_bookmarkTags":["read-it-later"],"_bookmarkLastModified":1440043064037000,"_bookmarkUrl":"http://bigocheatsheet.com/#data-structures","_bookmarkTitle":"Big-O Algorithm Complexity Cheat Sheet"},"http://wpweb2.tepper.cmu.edu/fmargot/index.html":{"_bookmarkDateAdded":1272081923000000,"_bookmarkTags":[],"_bookmarkLastModified":1438675426217000,"_bookmarkUrl":"http://wpweb2.tepper.cmu.edu/fmargot/index.html","_bookmarkTitle":"http://wpweb2.tepper.cmu.edu/fmargot/index.html"}}}}