{"_cloudLastModified":1438692804475979,"_cloudCreated":1438692794629457,"_store":{"store":{"http://web.mit.edu/asuman/www/":{"_bookmarkDateAdded":1276580387000000,"_bookmarkTags":[],"_bookmarkLastModified":1438675425500000,"_bookmarkUrl":"http://web.mit.edu/asuman/www/","_bookmarkTitle":"Asu Ozdaglar"},"http://www.theguardian.com/science/alexs-adventures-in-numberland/2014/oct/21/martin-gardner-mathematical-puzzles-birthday":{"_bookmarkDateAdded":1431350288202000,"_bookmarkTags":["puzzles"],"_bookmarkLastModified":1431350288350000,"_bookmarkUrl":"http://www.theguardian.com/science/alexs-adventures-in-numberland/2014/oct/21/martin-gardner-mathematical-puzzles-birthday","_bookmarkTitle":"Can you solve Martin Gardner’s best mathematical puzzles? | Science | The Guardian"}}}}