{"_cloudLastModified":1438692804538356,"_cloudCreated":1438692804537561,"_store":{"store":{"http://www2.research.att.com/%7Edsj/":{"_bookmarkDateAdded":1267721126000000,"_bookmarkTags":[],"_bookmarkLastModified":1438675426917000,"_bookmarkUrl":"http://www2.research.att.com/%7Edsj/","_bookmarkTitle":"David S. Johnson"},"https://simonsfoundation.org/features/science-news/in-computers-we-trust/":{"_bookmarkDateAdded":1367255122000000,"_bookmarkTags":[],"_bookmarkLastModified":1438675421606000,"_bookmarkUrl":"https://simonsfoundation.org/features/science-news/in-computers-we-trust/","_bookmarkTitle":"In Computers We Trust? | Simons Foundation"},"http://www.cs.rutgers.edu/%7Emlittman/":{"_bookmarkDateAdded":1252842454000000,"_bookmarkTags":[],"_bookmarkLastModified":1438675428380000,"_bookmarkUrl":"http://www.cs.rutgers.edu/%7Emlittman/","_bookmarkTitle":"Michael Littman's Home Page"},"http://www.math.ias.edu/%7Eavi/":{"_bookmarkDateAdded":1266237739000000,"_bookmarkTags":[],"_bookmarkLastModified":1438675427344000,"_bookmarkUrl":"http://www.math.ias.edu/%7Eavi/","_bookmarkTitle":"Avi Wigderson's Home Page"},"http://adamilab.blogspot.in/2013/04/what-is-information-part-i-eye-of.html":{"_bookmarkDateAdded":1369721493000000,"_bookmarkTags":[],"_bookmarkLastModified":1438675420958000,"_bookmarkUrl":"http://adamilab.blogspot.in/2013/04/what-is-information-part-i-eye-of.html","_bookmarkTitle":"Spherical Harmonics: What is Information? (Part I: The Eye of the Beholder)"}}}}