{"_cloudLastModified":1443676080752952,"_cloudCreated":1438692719644770,"_store":{"store":{"http://www.cs.princeton.edu/%7Ewayne/contact/":{"_bookmarkDateAdded":1271077285000000,"_bookmarkTags":[],"_bookmarkLastModified":1438675426577000,"_bookmarkUrl":"http://www.cs.princeton.edu/%7Ewayne/contact/","_bookmarkTitle":"Kevin Wayne: Contact Information"},"https://mtaptich.github.io/d3-lessons/":{"_bookmarkDateAdded":1442917620912000,"_bookmarkTags":["visualization"],"_bookmarkLastModified":1442917620943000,"_bookmarkUrl":"https://mtaptich.github.io/d3-lessons/","_bookmarkTitle":"An introduction to d3.js"},"http://www.cs.princeton.edu/courses/archive/spring06/cos345/":{"_bookmarkDateAdded":1281980116000000,"_bookmarkTags":[],"_bookmarkLastModified":1438675424768000,"_bookmarkUrl":"http://www.cs.princeton.edu/courses/archive/spring06/cos345/","_bookmarkTitle":"COS 345, Spring 2006: Home Page"},"http://papers.ssrn.com/sol3/papers.cfm?abstract_id=1968579":{"_bookmarkDateAdded":1414642056870634,"_bookmarkTags":[],"_bookmarkLastModified":1414642056883328,"_bookmarkUrl":"http://papers.ssrn.com/sol3/papers.cfm?abstract_id=1968579","_bookmarkTitle":"A Brief Introduction to the Basics of Game Theory by Matthew O. Jackson :: SSRN"}}}}